README.md
setup.cfg
setup.py
hu_wiwi_grades/__init__.py
hu_wiwi_grades/hu_wiwi_grades.py
hu_wiwi_grades.egg-info/PKG-INFO
hu_wiwi_grades.egg-info/SOURCES.txt
hu_wiwi_grades.egg-info/dependency_links.txt
hu_wiwi_grades.egg-info/requires.txt
hu_wiwi_grades.egg-info/top_level.txt