Metadata-Version: 2.1
Name: hu-wiwi-grades
Version: 0.1.0
Summary: hu_wiwi_grades is a Python library for searching, viewing and scraping published students grading of the Faculty of Economics and Business Administration of the Humboldt University of Berlin
Home-page: https://github.com/NDelventhal/hu_wiwi_grades
Author: Niall Delventhal
Author-email: ni.delventhal@gmail.com
License: MIT
Download-URL: https://github.com/NDelventhal/hu_wiwi_grades/archive/v_010.tar.gz
Platform: UNKNOWN
Classifier: Intended Audience :: Science/Research
Classifier: License :: OSI Approved :: MIT License
Classifier: Development Status :: 3 - Alpha
Classifier: Programming Language :: Python :: 3
Classifier: Programming Language :: Python :: 3.6
